[
  {
    "iso-a3": "AFG",
    "r": "",
    "g": "",
    "b": "",
    "temp-avg-x": "",
    "em-avg-y": "67,50910658",
    "temp-high-x": "",
    "em-high-y": "67,50910658",
    "temp-low-x": "",
    "em-low-y": "67,50910658",
    "em-high-y-min": "79,73080094",
    "em-high-y-max": "55,28741222",
    "em-low-y-min": "79,73080094",
    "em-low-y-max": "55,28741222"
  },
  {
    "iso-a3": "AGO",
    "r": "",
    "g": "",
    "b": "",
    "temp-avg-x": "",
    "em-avg-y": "-10,50857488",
    "temp-high-x": "",
    "em-high-y": "-19,85714484",
    "temp-low-x": "",
    "em-low-y": "-1,160004916",
    "em-high-y-min": "-19,85714484",
    "em-high-y-max": "-19,85714484",
    "em-low-y-min": "-1,160004916",
    "em-low-y-max": "-1,160004916"
  },
  {
    "iso-a3": "ALB",
    "r": "",
    "g": "",
    "b": "",
    "temp-avg-x": "",
    "em-avg-y": "26,09243366",
    "temp-high-x": "",
    "em-high-y": "26,09243366",
    "temp-low-x": "",
    "em-low-y": "26,09243366",
    "em-high-y-min": "26,09243366",
    "em-high-y-max": "26,09243366",
    "em-low-y-min": "26,09243366",
    "em-low-y-max": "26,09243366"
  },
  {
    "iso-a3": "AND",
    "r": "",
    "g": "",
    "b": "",
    "temp-avg-x": "",
    "em-avg-y": "-36,63037161",
    "temp-high-x": "",
    "em-high-y": "-36,63037161",
    "temp-low-x": "",
    "em-low-y": "-36,63037161",
    "em-high-y-min": "-36,63037161",
    "em-high-y-max": "-36,63037161",
    "em-low-y-min": "-36,63037161",
    "em-low-y-max": "-36,63037161"
  },
  {
    "iso-a3": "ARE",
    "r": "",
    "g": "",
    "b": "",
    "temp-avg-x": "",
    "em-avg-y": "6,684981035",
    "temp-high-x": "",
    "em-high-y": "6,684981035",
    "temp-low-x": "",
    "em-low-y": "6,684981035",
    "em-high-y-min": "6,684981035",
    "em-high-y-max": "6,684981035",
    "em-low-y-min": "6,684981035",
    "em-low-y-max": "6,684981035"
  },
  {
    "iso-a3": "ARG",
    "r": "0",
    "g": "1",
    "b": "1",
    "temp-avg-x": "",
    "em-avg-y": "-5,580733905",
    "temp-high-x": "",
    "em-high-y": "-5,580733905",
    "temp-low-x": "",
    "em-low-y": "-5,580733905",
    "em-high-y-min": "-5,580733905",
    "em-high-y-max": "-5,580733905",
    "em-low-y-min": "-5,580733905",
    "em-low-y-max": "-5,580733905"
  },
  {
    "iso-a3": "ARM",
    "r": "0",
    "g": "0",
    "b": "1",
    "temp-avg-x": "",
    "em-avg-y": "124,3479299",
    "temp-high-x": "",
    "em-high-y": "124,3479299",
    "temp-low-x": "",
    "em-low-y": "124,3479299",
    "em-high-y-min": "124,3479299",
    "em-high-y-max": "124,3479299",
    "em-low-y-min": "124,3479299",
    "em-low-y-max": "124,3479299"
  },
  {
    "iso-a3": "ATG",
    "r": "",
    "g": "",
    "b": "",
    "temp-avg-x": "",
    "em-avg-y": "35,81454525",
    "temp-high-x": "",
    "em-high-y": "35,81454525",
    "temp-low-x": "",
    "em-low-y": "35,81454525",
    "em-high-y-min": "35,81454525",
    "em-high-y-max": "35,81454525",
    "em-low-y-min": "35,81454525",
    "em-low-y-max": "35,81454525"
  },
  {
    "iso-a3": "AUS",
    "r": "0",
    "g": "0",
    "b": "0.6666666667",
    "temp-avg-x": "",
    "em-avg-y": "-38,99548295",
    "temp-high-x": "",
    "em-high-y": "-38,99548295",
    "temp-low-x": "",
    "em-low-y": "-38,99548295",
    "em-high-y-min": "-38,99548295",
    "em-high-y-max": "-38,99548295",
    "em-low-y-min": "-38,99548295",
    "em-low-y-max": "-38,99548295"
  },
  {
    "iso-a3": "AUT",
    "r": "0",
    "g": "0.3333333333",
    "b": "1",
    "temp-avg-x": "",
    "em-avg-y": "-52,98953073",
    "temp-high-x": "",
    "em-high-y": "-52,98953073",
    "temp-low-x": "",
    "em-low-y": "-52,98953073",
    "em-high-y-min": "-52,98953073",
    "em-high-y-max": "-52,98953073",
    "em-low-y-min": "-52,98953073",
    "em-low-y-max": "-52,98953073"
  },
  {
    "iso-a3": "AZE",
    "r": "0",
    "g": "0",
    "b": "1",
    "temp-avg-x": "",
    "em-avg-y": "24,40391972",
    "temp-high-x": "",
    "em-high-y": "24,40391972",
    "temp-low-x": "",
    "em-low-y": "24,40391972",
    "em-high-y-min": "24,40391972",
    "em-high-y-max": "24,40391972",
    "em-low-y-min": "24,40391972",
    "em-low-y-max": "24,40391972"
  },
  {
    "iso-a3": "BDI",
    "r": "0.3333333333",
    "g": "1",
    "b": "0.6666666667",
    "temp-avg-x": "",
    "em-avg-y": "48,59066397",
    "temp-high-x": "",
    "em-high-y": "40,87701104",
    "temp-low-x": "",
    "em-low-y": "56,3043169",
    "em-high-y-min": "40,87701104",
    "em-high-y-max": "40,87701104",
    "em-low-y-min": "56,3043169",
    "em-low-y-max": "56,3043169"
  },
  {
    "iso-a3": "BEL",
    "r": "0",
    "g": "0.3333333333",
    "b": "1",
    "temp-avg-x": "",
    "em-avg-y": "-47,56339218",
    "temp-high-x": "",
    "em-high-y": "-47,56339218",
    "temp-low-x": "",
    "em-low-y": "-47,56339218",
    "em-high-y-min": "-47,56339218",
    "em-high-y-max": "-47,56339218",
    "em-low-y-min": "-47,56339218",
    "em-low-y-max": "-47,56339218"
  },
  {
    "iso-a3": "BEN",
    "r": "0.3333333333",
    "g": "1",
    "b": "0.6666666667",
    "temp-avg-x": "",
    "em-avg-y": "143,1779579",
    "temp-high-x": "",
    "em-high-y": "130,3227419",
    "temp-low-x": "",
    "em-low-y": "156,0331739",
    "em-high-y-min": "130,3227419",
    "em-high-y-max": "130,3227419",
    "em-low-y-min": "156,0331739",
    "em-low-y-max": "156,0331739"
  },
  {
    "iso-a3": "BFA",
    "r": "0.3333333333",
    "g": "1",
    "b": "0.6666666667",
    "temp-avg-x": "",
    "em-avg-y": "237,1691625",
    "temp-high-x": "",
    "em-high-y": "215,5874143",
    "temp-low-x": "",
    "em-low-y": "258,7509106",
    "em-high-y-min": "215,5874143",
    "em-high-y-max": "215,5874143",
    "em-low-y-min": "258,7509106",
    "em-low-y-max": "258,7509106"
  },
  {
    "iso-a3": "BGD",
    "r": "1",
    "g": "1",
    "b": "0",
    "temp-avg-x": "",
    "em-avg-y": "99,34649987",
    "temp-high-x": "",
    "em-high-y": "80,87032425",
    "temp-low-x": "",
    "em-low-y": "117,8226755",
    "em-high-y-min": "80,87032425",
    "em-high-y-max": "80,87032425",
    "em-low-y-min": "117,8226755",
    "em-low-y-max": "117,8226755"
  },
  {
    "iso-a3": "BGR",
    "r": "0",
    "g": "0",
    "b": "1",
    "temp-avg-x": "",
    "em-avg-y": "-36,98957055",
    "temp-high-x": "",
    "em-high-y": "-36,98957055",
    "temp-low-x": "",
    "em-low-y": "-36,98957055",
    "em-high-y-min": "-36,98957055",
    "em-high-y-max": "-36,98957055",
    "em-low-y-min": "-36,98957055",
    "em-low-y-max": "-36,98957055"
  },
  {
    "iso-a3": "BHR",
    "r": "0.6666666667",
    "g": "1",
    "b": "0.3333333333",
    "temp-avg-x": "",
    "em-avg-y": "33,38347585",
    "temp-high-x": "",
    "em-high-y": "33,38347585",
    "temp-low-x": "",
    "em-low-y": "33,38347585",
    "em-high-y-min": "33,38347585",
    "em-high-y-max": "33,38347585",
    "em-low-y-min": "33,38347585",
    "em-low-y-max": "33,38347585"
  },
  {
    "iso-a3": "BHS",
    "r": "0",
    "g": "1",
    "b": "1",
    "temp-avg-x": "",
    "em-avg-y": "-8,770654844",
    "temp-high-x": "",
    "em-high-y": "-8,770654844",
    "temp-low-x": "",
    "em-low-y": "-8,770654844",
    "em-high-y-min": "14,89566468",
    "em-high-y-max": "-32,43697437",
    "em-low-y-min": "14,89566468",
    "em-low-y-max": "-32,43697437"
  },
  {
    "iso-a3": "BIH",
    "r": "0",
    "g": "0",
    "b": "1",
    "temp-avg-x": "",
    "em-avg-y": "-22,80717152",
    "temp-high-x": "",
    "em-high-y": "-24,92585603",
    "temp-low-x": "",
    "em-low-y": "-20,68848702",
    "em-high-y-min": "-24,92585603",
    "em-high-y-max": "-24,92585603",
    "em-low-y-min": "-20,68848702",
    "em-low-y-max": "-20,68848702"
  },
  {
    "iso-a3": "BLR",
    "r": "0",
    "g": "0",
    "b": "1",
    "temp-avg-x": "",
    "em-avg-y": "2,409632732",
    "temp-high-x": "",
    "em-high-y": "-0,343223153",
    "temp-low-x": "",
    "em-low-y": "5,162488617",
    "em-high-y-min": "-0,343223153",
    "em-high-y-max": "-0,343223153",
    "em-low-y-min": "5,162488617",
    "em-low-y-max": "5,162488617"
  },
  {
    "iso-a3": "BLZ",
    "r": "0",
    "g": "1",
    "b": "1",
    "temp-avg-x": "",
    "em-avg-y": "87,34003559",
    "temp-high-x": "",
    "em-high-y": "87,34003559",
    "temp-low-x": "",
    "em-low-y": "87,34003559",
    "em-high-y-min": "87,34003559",
    "em-high-y-max": "87,34003559",
    "em-low-y-min": "87,34003559",
    "em-low-y-max": "87,34003559"
  },
  {
    "iso-a3": "BOL",
    "r": "0",
    "g": "1",
    "b": "1",
    "temp-avg-x": "",
    "em-avg-y": "105,2852152",
    "temp-high-x": "",
    "em-high-y": "105,2852152",
    "temp-low-x": "",
    "em-low-y": "105,2852152",
    "em-high-y-min": "105,2852152",
    "em-high-y-max": "105,2852152",
    "em-low-y-min": "105,2852152",
    "em-low-y-max": "105,2852152"
  },
  {
    "iso-a3": "BRA",
    "r": "0",
    "g": "1",
    "b": "1",
    "temp-avg-x": "",
    "em-avg-y": "-23,85300577",
    "temp-high-x": "",
    "em-high-y": "-23,85300577",
    "temp-low-x": "",
    "em-low-y": "-23,85300577",
    "em-high-y-min": "-7,168753025",
    "em-high-y-max": "-40,53725851",
    "em-low-y-min": "-7,168753025",
    "em-low-y-max": "-40,53725851"
  },
  {
    "iso-a3": "BRB",
    "r": "0",
    "g": "1",
    "b": "1",
    "temp-avg-x": "",
    "em-avg-y": "-46,0147363",
    "temp-high-x": "",
    "em-high-y": "-65,67100242",
    "temp-low-x": "",
    "em-low-y": "-26,35847018",
    "em-high-y-min": "-65,67100242",
    "em-high-y-max": "-65,67100242",
    "em-low-y-min": "-26,35847018",
    "em-low-y-max": "-26,35847018"
  },
  {
    "iso-a3": "BRN",
    "r": "1",
    "g": "0.6666666667",
    "b": "0",
    "temp-avg-x": "",
    "em-avg-y": "68,14227272",
    "temp-high-x": "",
    "em-high-y": "68,14227272",
    "temp-low-x": "",
    "em-low-y": "68,14227272",
    "em-high-y-min": "68,14227272",
    "em-high-y-max": "68,14227272",
    "em-low-y-min": "68,14227272",
    "em-low-y-max": "68,14227272"
  },
  {
    "iso-a3": "BTN",
    "r": "1",
    "g": "1",
    "b": "0",
    "temp-avg-x": "",
    "em-avg-y": "97,50924563",
    "temp-high-x": "",
    "em-high-y": "97,50924563",
    "temp-low-x": "",
    "em-low-y": "97,50924563",
    "em-high-y-min": "97,50924563",
    "em-high-y-max": "97,50924563",
    "em-low-y-min": "97,50924563",
    "em-low-y-max": "97,50924563"
  },
  {
    "iso-a3": "BWA",
    "r": "0.3333333333",
    "g": "1",
    "b": "0.6666666667",
    "temp-avg-x": "",
    "em-avg-y": "-15,00000044",
    "temp-high-x": "",
    "em-high-y": "-15,00000044",
    "temp-low-x": "",
    "em-low-y": "-15,00000044",
    "em-high-y-min": "-15,00000044",
    "em-high-y-max": "-15,00000044",
    "em-low-y-min": "-15,00000044",
    "em-low-y-max": "-15,00000044"
  },
  {
    "iso-a3": "CAF",
    "r": "0.3333333333",
    "g": "1",
    "b": "0.6666666667",
    "temp-avg-x": "",
    "em-avg-y": "-28,05135864",
    "temp-high-x": "",
    "em-high-y": "-33,52103471",
    "temp-low-x": "",
    "em-low-y": "-22,58168257",
    "em-high-y-min": "-33,52103471",
    "em-high-y-max": "-33,52103471",
    "em-low-y-min": "-22,58168257",
    "em-low-y-max": "-22,58168257"
  },
  {
    "iso-a3": "CAN",
    "r": "0",
    "g": "0.6666666667",
    "b": "1",
    "temp-avg-x": "",
    "em-avg-y": "-39,63096311",
    "temp-high-x": "",
    "em-high-y": "-39,63096311",
    "temp-low-x": "",
    "em-low-y": "-39,63096311",
    "em-high-y-min": "-37,09571742",
    "em-high-y-max": "-42,16620879",
    "em-low-y-min": "-37,09571742",
    "em-low-y-max": "-42,16620879"
  },
  {
    "iso-a3": "CHE",
    "r": "0",
    "g": "0.3333333333",
    "b": "1",
    "temp-avg-x": "",
    "em-avg-y": "-46,59021436",
    "temp-high-x": "",
    "em-high-y": "-46,59021436",
    "temp-low-x": "",
    "em-low-y": "-46,59021436",
    "em-high-y-min": "-46,59021436",
    "em-high-y-max": "-46,59021436",
    "em-low-y-min": "-46,59021436",
    "em-low-y-max": "-46,59021436"
  },
  {
    "iso-a3": "CHL",
    "r": "0",
    "g": "1",
    "b": "1",
    "temp-avg-x": "",
    "em-avg-y": "-9,233013711",
    "temp-high-x": "",
    "em-high-y": "-9,233013711",
    "temp-low-x": "",
    "em-low-y": "-9,233013711",
    "em-high-y-min": "-9,233013711",
    "em-high-y-max": "-9,233013711",
    "em-low-y-min": "-9,233013711",
    "em-low-y-max": "-9,233013711"
  },
  {
    "iso-a3": "CHN",
    "r": "1",
    "g": "0.3333333333",
    "b": "0",
    "temp-avg-x": "",
    "em-avg-y": "38,36480961",
    "temp-high-x": "",
    "em-high-y": "38,36480961",
    "temp-low-x": "",
    "em-low-y": "38,36480961",
    "em-high-y-min": "42,27135674",
    "em-high-y-max": "34,45826249",
    "em-low-y-min": "42,27135674",
    "em-low-y-max": "34,45826249"
  },
  {
    "iso-a3": "CIV",
    "r": "0.3333333333",
    "g": "1",
    "b": "0.6666666667",
    "temp-avg-x": "",
    "em-avg-y": "91,60115506",
    "temp-high-x": "",
    "em-high-y": "81,41646443",
    "temp-low-x": "",
    "em-low-y": "101,7858457",
    "em-high-y-min": "81,41646443",
    "em-high-y-max": "81,41646443",
    "em-low-y-min": "101,7858457",
    "em-low-y-max": "101,7858457"
  },
  {
    "iso-a3": "CMR",
    "r": "0.3333333333",
    "g": "1",
    "b": "0.6666666667",
    "temp-avg-x": "",
    "em-avg-y": "171,3721328",
    "temp-high-x": "",
    "em-high-y": "131,511776",
    "temp-low-x": "",
    "em-low-y": "211,2324897",
    "em-high-y-min": "131,511776",
    "em-high-y-max": "131,511776",
    "em-low-y-min": "211,2324897",
    "em-low-y-max": "211,2324897"
  },
  {
    "iso-a3": "COD",
    "r": "0.3333333333",
    "g": "1",
    "b": "0.6666666667",
    "temp-avg-x": "",
    "em-avg-y": "117,4897133",
    "temp-high-x": "",
    "em-high-y": "97,48774894",
    "temp-low-x": "",
    "em-low-y": "137,4916776",
    "em-high-y-min": "97,48774894",
    "em-high-y-max": "97,48774894",
    "em-low-y-min": "137,4916776",
    "em-low-y-max": "137,4916776"
  },
  {
    "iso-a3": "COG",
    "r": "0.3333333333",
    "g": "1",
    "b": "0.6666666667",
    "temp-avg-x": "",
    "em-avg-y": "19,39922911",
    "temp-high-x": "",
    "em-high-y": "-33,75210322",
    "temp-low-x": "",
    "em-low-y": "72,55056144",
    "em-high-y-min": "-33,75210322",
    "em-high-y-max": "-33,75210322",
    "em-low-y-min": "72,55056144",
    "em-low-y-max": "72,55056144"
  },
  {
    "iso-a3": "COK",
    "r": "",
    "g": "",
    "b": "",
    "temp-avg-x": "",
    "em-avg-y": "33,05889546",
    "temp-high-x": "",
    "em-high-y": "25,23334013",
    "temp-low-x": "",
    "em-low-y": "40,88445078",
    "em-high-y-min": "25,23334013",
    "em-high-y-max": "25,23334013",
    "em-low-y-min": "40,88445078",
    "em-low-y-max": "40,88445078"
  },
  {
    "iso-a3": "COL",
    "r": "0",
    "g": "1",
    "b": "1",
    "temp-avg-x": "",
    "em-avg-y": "-18,35529446",
    "temp-high-x": "",
    "em-high-y": "-18,35529446",
    "temp-low-x": "",
    "em-low-y": "-18,35529446",
    "em-high-y-min": "-18,35529446",
    "em-high-y-max": "-18,35529446",
    "em-low-y-min": "-18,35529446",
    "em-low-y-max": "-18,35529446"
  },
  {
    "iso-a3": "COM",
    "r": "0.3333333333",
    "g": "1",
    "b": "0.6666666667",
    "temp-avg-x": "",
    "em-avg-y": "60,60880008",
    "temp-high-x": "",
    "em-high-y": "39,73870573",
    "temp-low-x": "",
    "em-low-y": "81,47889443",
    "em-high-y-min": "39,73870573",
    "em-high-y-max": "39,73870573",
    "em-low-y-min": "81,47889443",
    "em-low-y-max": "81,47889443"
  },
  {
    "iso-a3": "CPV",
    "r": "0.3333333333",
    "g": "1",
    "b": "0.6666666667",
    "temp-avg-x": "",
    "em-avg-y": "1,972695965",
    "temp-high-x": "",
    "em-high-y": "-1,899646211",
    "temp-low-x": "",
    "em-low-y": "5,845038141",
    "em-high-y-min": "-1,899646211",
    "em-high-y-max": "-1,899646211",
    "em-low-y-min": "5,845038141",
    "em-low-y-max": "5,845038141"
  },
  {
    "iso-a3": "CRI",
    "r": "0",
    "g": "1",
    "b": "1",
    "temp-avg-x": "",
    "em-avg-y": "-6,979490236",
    "temp-high-x": "",
    "em-high-y": "-6,979490236",
    "temp-low-x": "",
    "em-low-y": "-6,979490236",
    "em-high-y-min": "-6,979490236",
    "em-high-y-max": "-6,979490236",
    "em-low-y-min": "-6,979490236",
    "em-low-y-max": "-6,979490236"
  },
  {
    "iso-a3": "CUB",
    "r": "0",
    "g": "1",
    "b": "1",
    "temp-avg-x": "",
    "em-avg-y": "9,620540939",
    "temp-high-x": "",
    "em-high-y": "9,620540939",
    "temp-low-x": "",
    "em-low-y": "9,620540939",
    "em-high-y-min": "9,620540939",
    "em-high-y-max": "9,620540939",
    "em-low-y-min": "9,620540939",
    "em-low-y-max": "9,620540939"
  },
  {
    "iso-a3": "CYP",
    "r": "0",
    "g": "0",
    "b": "1",
    "temp-avg-x": "",
    "em-avg-y": "-48,49527078",
    "temp-high-x": "",
    "em-high-y": "-48,49527078",
    "temp-low-x": "",
    "em-low-y": "-48,49527078",
    "em-high-y-min": "-48,49527078",
    "em-high-y-max": "-48,49527078",
    "em-low-y-min": "-48,49527078",
    "em-low-y-max": "-48,49527078"
  },
  {
    "iso-a3": "CZE",
    "r": "0",
    "g": "0",
    "b": "1",
    "temp-avg-x": "",
    "em-avg-y": "-39,55674563",
    "temp-high-x": "",
    "em-high-y": "-39,55674563",
    "temp-low-x": "",
    "em-low-y": "-39,55674563",
    "em-high-y-min": "-39,55674563",
    "em-high-y-max": "-39,55674563",
    "em-low-y-min": "-39,55674563",
    "em-low-y-max": "-39,55674563"
  },
  {
    "iso-a3": "DEU",
    "r": "0",
    "g": "0.3333333333",
    "b": "1",
    "temp-avg-x": "",
    "em-avg-y": "-48,58499317",
    "temp-high-x": "",
    "em-high-y": "-48,58499317",
    "temp-low-x": "",
    "em-low-y": "-48,58499317",
    "em-high-y-min": "-48,58499317",
    "em-high-y-max": "-48,58499317",
    "em-low-y-min": "-48,58499317",
    "em-low-y-max": "-48,58499317"
  },
  {
    "iso-a3": "DJI",
    "r": "0.3333333333",
    "g": "1",
    "b": "0.6666666667",
    "temp-avg-x": "",
    "em-avg-y": "46,44925061",
    "temp-high-x": "",
    "em-high-y": "17,15941185",
    "temp-low-x": "",
    "em-low-y": "75,73908936",
    "em-high-y-min": "17,15941185",
    "em-high-y-max": "17,15941185",
    "em-low-y-min": "75,73908936",
    "em-low-y-max": "75,73908936"
  },
  {
    "iso-a3": "DMA",
    "r": "",
    "g": "",
    "b": "",
    "temp-avg-x": "",
    "em-avg-y": "-22,72278613",
    "temp-high-x": "",
    "em-high-y": "-45,158006",
    "temp-low-x": "",
    "em-low-y": "-0,287566257",
    "em-high-y-min": "-45,158006",
    "em-high-y-max": "-45,158006",
    "em-low-y-min": "-0,287566257",
    "em-low-y-max": "-0,287566257"
  },
  {
    "iso-a3": "DNK",
    "r": "0",
    "g": "0.3333333333",
    "b": "1",
    "temp-avg-x": "",
    "em-avg-y": "-44,70956267",
    "temp-high-x": "",
    "em-high-y": "-44,70956267",
    "temp-low-x": "",
    "em-low-y": "-44,70956267",
    "em-high-y-min": "-44,70956267",
    "em-high-y-max": "-44,70956267",
    "em-low-y-min": "-44,70956267",
    "em-low-y-max": "-44,70956267"
  },
  {
    "iso-a3": "DOM",
    "r": "0",
    "g": "1",
    "b": "1",
    "temp-avg-x": "",
    "em-avg-y": "24,72469259",
    "temp-high-x": "",
    "em-high-y": "9,697620758",
    "temp-low-x": "",
    "em-low-y": "39,75176443",
    "em-high-y-min": "9,697620758",
    "em-high-y-max": "9,697620758",
    "em-low-y-min": "39,75176443",
    "em-low-y-max": "39,75176443"
  },
  {
    "iso-a3": "DZA",
    "r": "0.6666666667",
    "g": "1",
    "b": "0.3333333333",
    "temp-avg-x": "",
    "em-avg-y": "60,03993783",
    "temp-high-x": "",
    "em-high-y": "46,33232915",
    "temp-low-x": "",
    "em-low-y": "73,74754651",
    "em-high-y-min": "46,33232915",
    "em-high-y-max": "46,33232915",
    "em-low-y-min": "73,74754651",
    "em-low-y-max": "73,74754651"
  },
  {
    "iso-a3": "ECU",
    "r": "0",
    "g": "1",
    "b": "1",
    "temp-avg-x": "",
    "em-avg-y": "0,202283685",
    "temp-high-x": "",
    "em-high-y": "-13,59514289",
    "temp-low-x": "",
    "em-low-y": "13,99971026",
    "em-high-y-min": "-13,59514289",
    "em-high-y-max": "-13,59514289",
    "em-low-y-min": "13,99971026",
    "em-low-y-max": "13,99971026"
  },
  {
    "iso-a3": "EGY",
    "r": "0.6666666667",
    "g": "1",
    "b": "0.3333333333",
    "temp-avg-x": "",
    "em-avg-y": "129,2491304",
    "temp-high-x": "",
    "em-high-y": "118,0749578",
    "temp-low-x": "",
    "em-low-y": "140,4233031",
    "em-high-y-min": "118,0749578",
    "em-high-y-max": "118,0749578",
    "em-low-y-min": "140,4233031",
    "em-low-y-max": "140,4233031"
  },
  {
    "iso-a3": "ERI",
    "r": "0.3333333333",
    "g": "1",
    "b": "0.6666666667",
    "temp-avg-x": "",
    "em-avg-y": "78,59034351",
    "temp-high-x": "",
    "em-high-y": "68,5133478",
    "temp-low-x": "",
    "em-low-y": "88,66733922",
    "em-high-y-min": "68,5133478",
    "em-high-y-max": "68,5133478",
    "em-low-y-min": "88,66733922",
    "em-low-y-max": "88,66733922"
  },
  {
    "iso-a3": "ESP",
    "r": "0",
    "g": "0.3333333333",
    "b": "1",
    "temp-avg-x": "",
    "em-avg-y": "-29,64266521",
    "temp-high-x": "",
    "em-high-y": "-29,64266521",
    "temp-low-x": "",
    "em-low-y": "-29,64266521",
    "em-high-y-min": "-29,64266521",
    "em-high-y-max": "-29,64266521",
    "em-low-y-min": "-29,64266521",
    "em-low-y-max": "-29,64266521"
  },
  {
    "iso-a3": "EST",
    "r": "0",
    "g": "0",
    "b": "1",
    "temp-avg-x": "",
    "em-avg-y": "-57,39271146",
    "temp-high-x": "",
    "em-high-y": "-57,39271146",
    "temp-low-x": "",
    "em-low-y": "-57,39271146",
    "em-high-y-min": "-57,39271146",
    "em-high-y-max": "-57,39271146",
    "em-low-y-min": "-57,39271146",
    "em-low-y-max": "-57,39271146"
  },
  {
    "iso-a3": "ETH",
    "r": "0.3333333333",
    "g": "1",
    "b": "0.6666666667",
    "temp-avg-x": "",
    "em-avg-y": "77,82384409",
    "temp-high-x": "",
    "em-high-y": "66,82011745",
    "temp-low-x": "",
    "em-low-y": "88,82757072",
    "em-high-y-min": "66,82011745",
    "em-high-y-max": "66,82011745",
    "em-low-y-min": "88,82757072",
    "em-low-y-max": "88,82757072"
  },
  {
    "iso-a3": "FIN",
    "r": "0",
    "g": "0.3333333333",
    "b": "1",
    "temp-avg-x": "",
    "em-avg-y": "-47,07989438",
    "temp-high-x": "",
    "em-high-y": "-47,07989438",
    "temp-low-x": "",
    "em-low-y": "-47,07989438",
    "em-high-y-min": "-47,07989438",
    "em-high-y-max": "-47,07989438",
    "em-low-y-min": "-47,07989438",
    "em-low-y-max": "-47,07989438"
  },
  {
    "iso-a3": "FJI",
    "r": "1",
    "g": "0.6666666667",
    "b": "0",
    "temp-avg-x": "",
    "em-avg-y": "4,0179121",
    "temp-high-x": "",
    "em-high-y": "-5,248468435",
    "temp-low-x": "",
    "em-low-y": "13,28429263",
    "em-high-y-min": "-5,248468435",
    "em-high-y-max": "-5,248468435",
    "em-low-y-min": "13,28429263",
    "em-low-y-max": "13,28429263"
  },
  {
    "iso-a3": "FRA",
    "r": "0",
    "g": "0.3333333333",
    "b": "1",
    "temp-avg-x": "",
    "em-avg-y": "-39,03141583",
    "temp-high-x": "",
    "em-high-y": "-39,03141583",
    "temp-low-x": "",
    "em-low-y": "-39,03141583",
    "em-high-y-min": "-39,03141583",
    "em-high-y-max": "-39,03141583",
    "em-low-y-min": "-39,03141583",
    "em-low-y-max": "-39,03141583"
  },
  {
    "iso-a3": "FSM",
    "r": "",
    "g": "",
    "b": "",
    "temp-avg-x": "",
    "em-avg-y": "-34,05728069",
    "temp-high-x": "",
    "em-high-y": "-39,54322005",
    "temp-low-x": "",
    "em-low-y": "-28,57134133",
    "em-high-y-min": "-39,54322005",
    "em-high-y-max": "-39,54322005",
    "em-low-y-min": "-28,57134133",
    "em-low-y-max": "-28,57134133"
  },
  {
    "iso-a3": "GAB",
    "r": "0.3333333333",
    "g": "1",
    "b": "0.6666666667",
    "temp-avg-x": "",
    "em-avg-y": "-15,87109295",
    "temp-high-x": "",
    "em-high-y": "-15,87109295",
    "temp-low-x": "",
    "em-low-y": "-15,87109295",
    "em-high-y-min": "-15,87109295",
    "em-high-y-max": "-15,87109295",
    "em-low-y-min": "-15,87109295",
    "em-low-y-max": "-15,87109295"
  },
  {
    "iso-a3": "GBR",
    "r": "0",
    "g": "0.3333333333",
    "b": "1",
    "temp-avg-x": "",
    "em-avg-y": "-57,34764126",
    "temp-high-x": "",
    "em-high-y": "-57,34764126",
    "temp-low-x": "",
    "em-low-y": "-57,34764126",
    "em-high-y-min": "-57,34764126",
    "em-high-y-max": "-57,34764126",
    "em-low-y-min": "-57,34764126",
    "em-low-y-max": "-57,34764126"
  },
  {
    "iso-a3": "GEO",
    "r": "0",
    "g": "0",
    "b": "1",
    "temp-avg-x": "",
    "em-avg-y": "0,520189977",
    "temp-high-x": "",
    "em-high-y": "-8,673010497",
    "temp-low-x": "",
    "em-low-y": "9,713390452",
    "em-high-y-min": "-5,194499328",
    "em-high-y-max": "-12,15152167",
    "em-low-y-min": "9,713390452",
    "em-low-y-max": "9,713390452"
  },
  {
    "iso-a3": "GHA",
    "r": "0.3333333333",
    "g": "1",
    "b": "0.6666666667",
    "temp-avg-x": "",
    "em-avg-y": "172,379503",
    "temp-high-x": "",
    "em-high-y": "152,0955144",
    "temp-low-x": "",
    "em-low-y": "192,6634916",
    "em-high-y-min": "152,0955144",
    "em-high-y-max": "152,0955144",
    "em-low-y-min": "192,6634916",
    "em-low-y-max": "192,6634916"
  },
  {
    "iso-a3": "GIN",
    "r": "0.3333333333",
    "g": "1",
    "b": "0.6666666667",
    "temp-avg-x": "",
    "em-avg-y": "124,307518",
    "temp-high-x": "",
    "em-high-y": "113,8992943",
    "temp-low-x": "",
    "em-low-y": "134,7157417",
    "em-high-y-min": "113,8992943",
    "em-high-y-max": "113,8992943",
    "em-low-y-min": "134,7157417",
    "em-low-y-max": "134,7157417"
  },
  {
    "iso-a3": "GMB",
    "r": "0.3333333333",
    "g": "1",
    "b": "0.6666666667",
    "temp-avg-x": "",
    "em-avg-y": "72,03818337",
    "temp-high-x": "",
    "em-high-y": "17,40791477",
    "temp-low-x": "",
    "em-low-y": "126,668452",
    "em-high-y-min": "17,40791477",
    "em-high-y-max": "17,40791477",
    "em-low-y-min": "126,668452",
    "em-low-y-max": "126,668452"
  },
  {
    "iso-a3": "GNB",
    "r": "0.3333333333",
    "g": "1",
    "b": "0.6666666667",
    "temp-avg-x": "",
    "em-avg-y": "269,6790466",
    "temp-high-x": "",
    "em-high-y": "201,4531314",
    "temp-low-x": "",
    "em-low-y": "337,9049619",
    "em-high-y-min": "201,4531314",
    "em-high-y-max": "201,4531314",
    "em-low-y-min": "337,9049619",
    "em-low-y-max": "337,9049619"
  },
  {
    "iso-a3": "GNQ",
    "r": "0.3333333333",
    "g": "1",
    "b": "0.6666666667",
    "temp-avg-x": "",
    "em-avg-y": "-20,00000197",
    "temp-high-x": "",
    "em-high-y": "-20,00000197",
    "temp-low-x": "",
    "em-low-y": "-20,00000197",
    "em-high-y-min": "-20,00000197",
    "em-high-y-max": "-20,00000197",
    "em-low-y-min": "-20,00000197",
    "em-low-y-max": "-20,00000197"
  },
  {
    "iso-a3": "GRC",
    "r": "0",
    "g": "0.3333333333",
    "b": "1",
    "temp-avg-x": "",
    "em-avg-y": "-32,63629057",
    "temp-high-x": "",
    "em-high-y": "-32,63629057",
    "temp-low-x": "",
    "em-low-y": "-32,63629057",
    "em-high-y-min": "-32,63629057",
    "em-high-y-max": "-32,63629057",
    "em-low-y-min": "-32,63629057",
    "em-low-y-max": "-32,63629057"
  },
  {
    "iso-a3": "GRD",
    "r": "",
    "g": "",
    "b": "",
    "temp-avg-x": "",
    "em-avg-y": "19,37945238",
    "temp-high-x": "",
    "em-high-y": "-36,31556667",
    "temp-low-x": "",
    "em-low-y": "75,07447143",
    "em-high-y-min": "-36,31556667",
    "em-high-y-max": "-36,31556667",
    "em-low-y-min": "75,07447143",
    "em-low-y-max": "75,07447143"
  },
  {
    "iso-a3": "GTM",
    "r": "0",
    "g": "1",
    "b": "1",
    "temp-avg-x": "",
    "em-avg-y": "136,6710902",
    "temp-high-x": "",
    "em-high-y": "121,9480803",
    "temp-low-x": "",
    "em-low-y": "151,3941",
    "em-high-y-min": "121,9480803",
    "em-high-y-max": "121,9480803",
    "em-low-y-min": "151,3941",
    "em-low-y-max": "151,3941"
  },
  {
    "iso-a3": "GUY",
    "r": "0",
    "g": "1",
    "b": "1",
    "temp-avg-x": "",
    "em-avg-y": "39,24571059",
    "temp-high-x": "",
    "em-high-y": "-0,177230256",
    "temp-low-x": "",
    "em-low-y": "78,66865144",
    "em-high-y-min": "-0,177230256",
    "em-high-y-max": "-0,177230256",
    "em-low-y-min": "78,66865144",
    "em-low-y-max": "78,66865144"
  },
  {
    "iso-a3": "HND",
    "r": "0",
    "g": "1",
    "b": "1",
    "temp-avg-x": "",
    "em-avg-y": "43,15487113",
    "temp-high-x": "",
    "em-high-y": "30,70662135",
    "temp-low-x": "",
    "em-low-y": "55,60312091",
    "em-high-y-min": "30,70662135",
    "em-high-y-max": "30,70662135",
    "em-low-y-min": "55,60312091",
    "em-low-y-max": "55,60312091"
  },
  {
    "iso-a3": "HRV",
    "r": "0",
    "g": "0",
    "b": "1",
    "temp-avg-x": "",
    "em-avg-y": "-18,87469496",
    "temp-high-x": "",
    "em-high-y": "-18,87469496",
    "temp-low-x": "",
    "em-low-y": "-18,87469496",
    "em-high-y-min": "-18,87469496",
    "em-high-y-max": "-18,87469496",
    "em-low-y-min": "-18,87469496",
    "em-low-y-max": "-18,87469496"
  },
  {
    "iso-a3": "HTI",
    "r": "0",
    "g": "1",
    "b": "1",
    "temp-avg-x": "",
    "em-avg-y": "29,35850311",
    "temp-high-x": "",
    "em-high-y": "7,566219773",
    "temp-low-x": "",
    "em-low-y": "51,15078645",
    "em-high-y-min": "7,566219773",
    "em-high-y-max": "7,566219773",
    "em-low-y-min": "51,15078645",
    "em-low-y-max": "51,15078645"
  },
  {
    "iso-a3": "HUN",
    "r": "0",
    "g": "0",
    "b": "1",
    "temp-avg-x": "",
    "em-avg-y": "-19,10793023",
    "temp-high-x": "",
    "em-high-y": "-19,10793023",
    "temp-low-x": "",
    "em-low-y": "-19,10793023",
    "em-high-y-min": "-19,10793023",
    "em-high-y-max": "-19,10793023",
    "em-low-y-min": "-19,10793023",
    "em-low-y-max": "-19,10793023"
  },
  {
    "iso-a3": "IDN",
    "r": "1",
    "g": "0.6666666667",
    "b": "0",
    "temp-avg-x": "",
    "em-avg-y": "23,25707622",
    "temp-high-x": "",
    "em-high-y": "2,858005573",
    "temp-low-x": "",
    "em-low-y": "43,65614687",
    "em-high-y-min": "2,858005573",
    "em-high-y-max": "2,858005573",
    "em-low-y-min": "43,65614687",
    "em-low-y-max": "43,65614687"
  },
  {
    "iso-a3": "IND",
    "r": "1",
    "g": "1",
    "b": "0",
    "temp-avg-x": "",
    "em-avg-y": "87,15347579",
    "temp-high-x": "",
    "em-high-y": "87,15347579",
    "temp-low-x": "",
    "em-low-y": "87,15347579",
    "em-high-y-min": "108,0040291",
    "em-high-y-max": "66,30292245",
    "em-low-y-min": "108,0040291",
    "em-low-y-max": "66,30292245"
  },
  {
    "iso-a3": "IRL",
    "r": "0",
    "g": "0.3333333333",
    "b": "1",
    "temp-avg-x": "",
    "em-avg-y": "-34,29224351",
    "temp-high-x": "",
    "em-high-y": "-34,29224351",
    "temp-low-x": "",
    "em-low-y": "-34,29224351",
    "em-high-y-min": "-34,29224351",
    "em-high-y-max": "-34,29224351",
    "em-low-y-min": "-34,29224351",
    "em-low-y-max": "-34,29224351"
  },
  {
    "iso-a3": "IRN",
    "r": "0.6666666667",
    "g": "1",
    "b": "0.3333333333",
    "temp-avg-x": "",
    "em-avg-y": "41,55431674",
    "temp-high-x": "",
    "em-high-y": "35,39978122",
    "temp-low-x": "",
    "em-low-y": "47,70885227",
    "em-high-y-min": "35,39978122",
    "em-high-y-max": "35,39978122",
    "em-low-y-min": "47,70885227",
    "em-low-y-max": "47,70885227"
  },
  {
    "iso-a3": "IRQ",
    "r": "0.6666666667",
    "g": "1",
    "b": "0.3333333333",
    "temp-avg-x": "",
    "em-avg-y": "203,3176715",
    "temp-high-x": "",
    "em-high-y": "203,3176715",
    "temp-low-x": "",
    "em-low-y": "203,3176715",
    "em-high-y-min": "203,3176715",
    "em-high-y-max": "203,3176715",
    "em-low-y-min": "203,3176715",
    "em-low-y-max": "203,3176715"
  },
  {
    "iso-a3": "ISL",
    "r": "0",
    "g": "0.3333333333",
    "b": "1",
    "temp-avg-x": "",
    "em-avg-y": "-57,09788615",
    "temp-high-x": "",
    "em-high-y": "-57,09788615",
    "temp-low-x": "",
    "em-low-y": "-57,09788615",
    "em-high-y-min": "-57,09788615",
    "em-high-y-max": "-57,09788615",
    "em-low-y-min": "-57,09788615",
    "em-low-y-max": "-57,09788615"
  },
  {
    "iso-a3": "ISR",
    "r": "0.6666666667",
    "g": "1",
    "b": "0.3333333333",
    "temp-avg-x": "",
    "em-avg-y": "-22,78010551",
    "temp-high-x": "",
    "em-high-y": "-22,78010551",
    "temp-low-x": "",
    "em-low-y": "-22,78010551",
    "em-high-y-min": "-22,78010551",
    "em-high-y-max": "-22,78010551",
    "em-low-y-min": "-22,78010551",
    "em-low-y-max": "-22,78010551"
  },
  {
    "iso-a3": "ITA",
    "r": "0",
    "g": "0.3333333333",
    "b": "1",
    "temp-avg-x": "",
    "em-avg-y": "-36,27723175",
    "temp-high-x": "",
    "em-high-y": "-36,27723175",
    "temp-low-x": "",
    "em-low-y": "-36,27723175",
    "em-high-y-min": "-36,27723175",
    "em-high-y-max": "-36,27723175",
    "em-low-y-min": "-36,27723175",
    "em-low-y-max": "-36,27723175"
  },
  {
    "iso-a3": "JAM",
    "r": "0",
    "g": "1",
    "b": "1",
    "temp-avg-x": "",
    "em-avg-y": "-11,1024089",
    "temp-high-x": "",
    "em-high-y": "-12,46543328",
    "temp-low-x": "",
    "em-low-y": "-9,73938451",
    "em-high-y-min": "-12,46543328",
    "em-high-y-max": "-12,46543328",
    "em-low-y-min": "-9,73938451",
    "em-low-y-max": "-9,73938451"
  },
  {
    "iso-a3": "JOR",
    "r": "0.6666666667",
    "g": "1",
    "b": "0.3333333333",
    "temp-avg-x": "",
    "em-avg-y": "45,97511778",
    "temp-high-x": "",
    "em-high-y": "22,83272157",
    "temp-low-x": "",
    "em-low-y": "69,11751399",
    "em-high-y-min": "22,83272157",
    "em-high-y-max": "22,83272157",
    "em-low-y-min": "69,11751399",
    "em-low-y-max": "69,11751399"
  },
  {
    "iso-a3": "JPN",
    "r": "0",
    "g": "0",
    "b": "0.6666666667",
    "temp-avg-x": "",
    "em-avg-y": "-44,80677907",
    "temp-high-x": "",
    "em-high-y": "-44,80677907",
    "temp-low-x": "",
    "em-low-y": "-44,80677907",
    "em-high-y-min": "-42,79517296",
    "em-high-y-max": "-46,81838519",
    "em-low-y-min": "-42,79517296",
    "em-low-y-max": "-46,81838519"
  },
  {
    "iso-a3": "KAZ",
    "r": "0",
    "g": "0",
    "b": "1",
    "temp-avg-x": "",
    "em-avg-y": "-11,62711265",
    "temp-high-x": "",
    "em-high-y": "-17,15041804",
    "temp-low-x": "",
    "em-low-y": "-6,103807271",
    "em-high-y-min": "-17,15041804",
    "em-high-y-max": "-17,15041804",
    "em-low-y-min": "-6,103807271",
    "em-low-y-max": "-6,103807271"
  },
  {
    "iso-a3": "KEN",
    "r": "0.3333333333",
    "g": "1",
    "b": "0.6666666667",
    "temp-avg-x": "",
    "em-avg-y": "80,64955575",
    "temp-high-x": "",
    "em-high-y": "52,33345488",
    "temp-low-x": "",
    "em-low-y": "108,9656566",
    "em-high-y-min": "52,33345488",
    "em-high-y-max": "52,33345488",
    "em-low-y-min": "108,9656566",
    "em-low-y-max": "108,9656566"
  },
  {
    "iso-a3": "KGZ",
    "r": "0",
    "g": "0",
    "b": "1",
    "temp-avg-x": "",
    "em-avg-y": "77,41222551",
    "temp-high-x": "",
    "em-high-y": "63,10005708",
    "temp-low-x": "",
    "em-low-y": "91,72439394",
    "em-high-y-min": "71,23432828",
    "em-high-y-max": "54,96578588",
    "em-low-y-min": "93,14334722",
    "em-low-y-max": "90,30544066"
  },
  {
    "iso-a3": "KHM",
    "r": "1",
    "g": "0.6666666667",
    "b": "0",
    "temp-avg-x": "",
    "em-avg-y": "106,2517982",
    "temp-high-x": "",
    "em-high-y": "65,30276245",
    "temp-low-x": "",
    "em-low-y": "147,2008339",
    "em-high-y-min": "65,30276245",
    "em-high-y-max": "65,30276245",
    "em-low-y-min": "147,2008339",
    "em-low-y-max": "147,2008339"
  },
  {
    "iso-a3": "KIR",
    "r": "",
    "g": "",
    "b": "",
    "temp-avg-x": "",
    "em-avg-y": "8,386727948",
    "temp-high-x": "",
    "em-high-y": "-13,56751494",
    "temp-low-x": "",
    "em-low-y": "30,34097084",
    "em-high-y-min": "-13,56751494",
    "em-high-y-max": "-13,56751494",
    "em-low-y-min": "30,34097084",
    "em-low-y-max": "30,34097084"
  },
  {
    "iso-a3": "KNA",
    "r": "",
    "g": "",
    "b": "",
    "temp-avg-x": "",
    "em-avg-y": "1,775985221",
    "temp-high-x": "",
    "em-high-y": "-34,79048965",
    "temp-low-x": "",
    "em-low-y": "38,34246009",
    "em-high-y-min": "-34,79048965",
    "em-high-y-max": "-34,79048965",
    "em-low-y-min": "38,34246009",
    "em-low-y-max": "38,34246009"
  },
  {
    "iso-a3": "KOR",
    "r": "1",
    "g": "0.3333333333",
    "b": "0",
    "temp-avg-x": "",
    "em-avg-y": "-32,88951209",
    "temp-high-x": "",
    "em-high-y": "-32,88951209",
    "temp-low-x": "",
    "em-low-y": "-32,88951209",
    "em-high-y-min": "-32,88951209",
    "em-high-y-max": "-32,88951209",
    "em-low-y-min": "-32,88951209",
    "em-low-y-max": "-32,88951209"
  },
  {
    "iso-a3": "KWT",
    "r": "0.6666666667",
    "g": "1",
    "b": "0.3333333333",
    "temp-avg-x": "",
    "em-avg-y": "17,18138577",
    "temp-high-x": "",
    "em-high-y": "17,18138577",
    "temp-low-x": "",
    "em-low-y": "17,18138577",
    "em-high-y-min": "17,18138577",
    "em-high-y-max": "17,18138577",
    "em-low-y-min": "17,18138577",
    "em-low-y-max": "17,18138577"
  },
  {
    "iso-a3": "LAO",
    "r": "1",
    "g": "0.6666666667",
    "b": "0",
    "temp-avg-x": "",
    "em-avg-y": "120,7647333",
    "temp-high-x": "",
    "em-high-y": "120,7647333",
    "temp-low-x": "",
    "em-low-y": "120,7647333",
    "em-high-y-min": "120,7647333",
    "em-high-y-max": "120,7647333",
    "em-low-y-min": "120,7647333",
    "em-low-y-max": "120,7647333"
  },
  {
    "iso-a3": "LBN",
    "r": "0.6666666667",
    "g": "1",
    "b": "0.3333333333",
    "temp-avg-x": "",
    "em-avg-y": "22,15169676",
    "temp-high-x": "",
    "em-high-y": "13,1784554",
    "temp-low-x": "",
    "em-low-y": "31,12493812",
    "em-high-y-min": "13,1784554",
    "em-high-y-max": "13,1784554",
    "em-low-y-min": "31,12493812",
    "em-low-y-max": "31,12493812"
  },
  {
    "iso-a3": "LBR",
    "r": "0.3333333333",
    "g": "1",
    "b": "0.6666666667",
    "temp-avg-x": "",
    "em-avg-y": "180,2115454",
    "temp-high-x": "",
    "em-high-y": "60,12089205",
    "temp-low-x": "",
    "em-low-y": "300,3021987",
    "em-high-y-min": "60,12089205",
    "em-high-y-max": "60,12089205",
    "em-low-y-min": "300,3021987",
    "em-low-y-max": "300,3021987"
  },
  {
    "iso-a3": "LBY",
    "r": "0.6666666667",
    "g": "1",
    "b": "0.3333333333",
    "temp-avg-x": "",
    "em-avg-y": "-1,231472561",
    "temp-high-x": "",
    "em-high-y": "-1,231472561",
    "temp-low-x": "",
    "em-low-y": "-1,231472561",
    "em-high-y-min": "-1,231472561",
    "em-high-y-max": "-1,231472561",
    "em-low-y-min": "-1,231472561",
    "em-low-y-max": "-1,231472561"
  },
  {
    "iso-a3": "LCA",
    "r": "0",
    "g": "1",
    "b": "1",
    "temp-avg-x": "",
    "em-avg-y": "29,28976447",
    "temp-high-x": "",
    "em-high-y": "29,28976447",
    "temp-low-x": "",
    "em-low-y": "29,28976447",
    "em-high-y-min": "29,28976447",
    "em-high-y-max": "29,28976447",
    "em-low-y-min": "29,28976447",
    "em-low-y-max": "29,28976447"
  },
  {
    "iso-a3": "LIE",
    "r": "",
    "g": "",
    "b": "",
    "temp-avg-x": "",
    "em-avg-y": "-33,50512394",
    "temp-high-x": "",
    "em-high-y": "-33,50512394",
    "temp-low-x": "",
    "em-low-y": "-33,50512394",
    "em-high-y-min": "-33,50512394",
    "em-high-y-max": "-33,50512394",
    "em-low-y-min": "-33,50512394",
    "em-low-y-max": "-33,50512394"
  },
  {
    "iso-a3": "LKA",
    "r": "1",
    "g": "1",
    "b": "0",
    "temp-avg-x": "",
    "em-avg-y": "70,52230271",
    "temp-high-x": "",
    "em-high-y": "59,24496234",
    "temp-low-x": "",
    "em-low-y": "81,79964309",
    "em-high-y-min": "59,24496234",
    "em-high-y-max": "59,24496234",
    "em-low-y-min": "81,79964309",
    "em-low-y-max": "81,79964309"
  },
  {
    "iso-a3": "LSO",
    "r": "0.3333333333",
    "g": "1",
    "b": "0.6666666667",
    "temp-avg-x": "",
    "em-avg-y": "2,165597216",
    "temp-high-x": "",
    "em-high-y": "-14,3127263",
    "temp-low-x": "",
    "em-low-y": "18,64392073",
    "em-high-y-min": "-14,3127263",
    "em-high-y-max": "-14,3127263",
    "em-low-y-min": "18,64392073",
    "em-low-y-max": "18,64392073"
  },
  {
    "iso-a3": "LTU",
    "r": "0",
    "g": "0",
    "b": "1",
    "temp-avg-x": "",
    "em-avg-y": "-23,82194412",
    "temp-high-x": "",
    "em-high-y": "-23,82194412",
    "temp-low-x": "",
    "em-low-y": "-23,82194412",
    "em-high-y-min": "-23,82194412",
    "em-high-y-max": "-23,82194412",
    "em-low-y-min": "-23,82194412",
    "em-low-y-max": "-23,82194412"
  },
  {
    "iso-a3": "LUX",
    "r": "0",
    "g": "0.3333333333",
    "b": "1",
    "temp-avg-x": "",
    "em-avg-y": "-35,67194265",
    "temp-high-x": "",
    "em-high-y": "-35,67194265",
    "temp-low-x": "",
    "em-low-y": "-35,67194265",
    "em-high-y-min": "-35,67194265",
    "em-high-y-max": "-35,67194265",
    "em-low-y-min": "-35,67194265",
    "em-low-y-max": "-35,67194265"
  },
  {
    "iso-a3": "LVA",
    "r": "0",
    "g": "0",
    "b": "1",
    "temp-avg-x": "",
    "em-avg-y": "-14,41586719",
    "temp-high-x": "",
    "em-high-y": "-14,41586719",
    "temp-low-x": "",
    "em-low-y": "-14,41586719",
    "em-high-y-min": "-14,41586719",
    "em-high-y-max": "-14,41586719",
    "em-low-y-min": "-14,41586719",
    "em-low-y-max": "-14,41586719"
  },
  {
    "iso-a3": "MAR",
    "r": "0.6666666667",
    "g": "1",
    "b": "0.3333333333",
    "temp-avg-x": "",
    "em-avg-y": "2,90794153",
    "temp-high-x": "",
    "em-high-y": "-19,77412015",
    "temp-low-x": "",
    "em-low-y": "25,59000321",
    "em-high-y-min": "-19,77412015",
    "em-high-y-max": "-19,77412015",
    "em-low-y-min": "25,59000321",
    "em-low-y-max": "25,59000321"
  },
  {
    "iso-a3": "MCO",
    "r": "",
    "g": "",
    "b": "",
    "temp-avg-x": "",
    "em-avg-y": "-48,65102377",
    "temp-high-x": "",
    "em-high-y": "-48,65102377",
    "temp-low-x": "",
    "em-low-y": "-48,65102377",
    "em-high-y-min": "-48,65102377",
    "em-high-y-max": "-48,65102377",
    "em-low-y-min": "-48,65102377",
    "em-low-y-max": "-48,65102377"
  },
  {
    "iso-a3": "MDA",
    "r": "0",
    "g": "0",
    "b": "1",
    "temp-avg-x": "",
    "em-avg-y": "16,1617815",
    "temp-high-x": "",
    "em-high-y": "-33,75949459",
    "temp-low-x": "",
    "em-low-y": "66,08305759",
    "em-high-y-min": "-33,75949459",
    "em-high-y-max": "-33,75949459",
    "em-low-y-min": "66,08305759",
    "em-low-y-max": "66,08305759"
  },
  {
    "iso-a3": "MDG",
    "r": "0.3333333333",
    "g": "1",
    "b": "0.6666666667",
    "temp-avg-x": "",
    "em-avg-y": "-3,688926374",
    "temp-high-x": "",
    "em-high-y": "-14,38877817",
    "temp-low-x": "",
    "em-low-y": "7,01092542",
    "em-high-y-min": "-14,38877817",
    "em-high-y-max": "-14,38877817",
    "em-low-y-min": "7,01092542",
    "em-low-y-max": "7,01092542"
  },
  {
    "iso-a3": "MDV",
    "r": "1",
    "g": "1",
    "b": "0",
    "temp-avg-x": "",
    "em-avg-y": "116,9876111",
    "temp-high-x": "",
    "em-high-y": "19,36655133",
    "temp-low-x": "",
    "em-low-y": "214,6086708",
    "em-high-y-min": "134,0325963",
    "em-high-y-max": "-95,29949359",
    "em-low-y-min": "214,6086708",
    "em-low-y-max": "214,6086708"
  },
  {
    "iso-a3": "MEX",
    "r": "0",
    "g": "1",
    "b": "1",
    "temp-avg-x": "",
    "em-avg-y": "-1,43987117",
    "temp-high-x": "",
    "em-high-y": "-9,853644243",
    "temp-low-x": "",
    "em-low-y": "6,973901903",
    "em-high-y-min": "-9,853644243",
    "em-high-y-max": "-9,853644243",
    "em-low-y-min": "6,973901903",
    "em-low-y-max": "6,973901903"
  },
  {
    "iso-a3": "MHL",
    "r": "",
    "g": "",
    "b": "",
    "temp-avg-x": "",
    "em-avg-y": "-45,00025268",
    "temp-high-x": "",
    "em-high-y": "-45,00025268",
    "temp-low-x": "",
    "em-low-y": "-45,00025268",
    "em-high-y-min": "-45,00025268",
    "em-high-y-max": "-45,00025268",
    "em-low-y-min": "-45,00025268",
    "em-low-y-max": "-45,00025268"
  },
  {
    "iso-a3": "MKD",
    "r": "0",
    "g": "0",
    "b": "1",
    "temp-avg-x": "",
    "em-avg-y": "-44,56649876",
    "temp-high-x": "",
    "em-high-y": "-44,56649876",
    "temp-low-x": "",
    "em-low-y": "-44,56649876",
    "em-high-y-min": "-44,56649876",
    "em-high-y-max": "-44,56649876",
    "em-low-y-min": "-44,56649876",
    "em-low-y-max": "-44,56649876"
  },
  {
    "iso-a3": "MLI",
    "r": "0.3333333333",
    "g": "1",
    "b": "0.6666666667",
    "temp-avg-x": "",
    "em-avg-y": "176,7881991",
    "temp-high-x": "",
    "em-high-y": "138,8666116",
    "temp-low-x": "",
    "em-low-y": "214,7097865",
    "em-high-y-min": "138,8666116",
    "em-high-y-max": "138,8666116",
    "em-low-y-min": "214,7097865",
    "em-low-y-max": "214,7097865"
  },
  {
    "iso-a3": "MLT",
    "r": "0",
    "g": "0",
    "b": "1",
    "temp-avg-x": "",
    "em-avg-y": "-50,13804",
    "temp-high-x": "",
    "em-high-y": "-50,13804",
    "temp-low-x": "",
    "em-low-y": "-50,13804",
    "em-high-y-min": "-50,13804",
    "em-high-y-max": "-50,13804",
    "em-low-y-min": "-50,13804",
    "em-low-y-max": "-50,13804"
  },
  {
    "iso-a3": "MNR",
    "r": "",
    "g": "",
    "b": "",
    "temp-avg-x": "",
    "em-avg-y": "24,16737747",
    "temp-high-x": "",
    "em-high-y": "20,49684591",
    "temp-low-x": "",
    "em-low-y": "27,83790904",
    "em-high-y-min": "20,49684591",
    "em-high-y-max": "20,49684591",
    "em-low-y-min": "27,83790904",
    "em-low-y-max": "27,83790904"
  },
  {
    "iso-a3": "MNE",
    "r": "",
    "g": "",
    "b": "",
    "temp-avg-x": "",
    "em-avg-y": "-20,78308814",
    "temp-high-x": "",
    "em-high-y": "-20,78308814",
    "temp-low-x": "",
    "em-low-y": "-20,78308814",
    "em-high-y-min": "-20,78308814",
    "em-high-y-max": "-20,78308814",
    "em-low-y-min": "-20,78308814",
    "em-low-y-max": "-20,78308814"
  },
  {
    "iso-a3": "MNG",
    "r": "1",
    "g": "0.3333333333",
    "b": "0",
    "temp-avg-x": "",
    "em-avg-y": "46,28200354",
    "temp-high-x": "",
    "em-high-y": "41,89646701",
    "temp-low-x": "",
    "em-low-y": "50,66754006",
    "em-high-y-min": "41,89646701",
    "em-high-y-max": "41,89646701",
    "em-low-y-min": "50,66754006",
    "em-low-y-max": "50,66754006"
  },
  {
    "iso-a3": "MOZ",
    "r": "0.3333333333",
    "g": "1",
    "b": "0.6666666667",
    "temp-avg-x": "",
    "em-avg-y": "91,63319861",
    "temp-high-x": "",
    "em-high-y": "-3,824245069",
    "temp-low-x": "",
    "em-low-y": "187,0906423",
    "em-high-y-min": "-3,824245069",
    "em-high-y-max": "-3,824245069",
    "em-low-y-min": "187,0906423",
    "em-low-y-max": "187,0906423"
  },
  {
    "iso-a3": "MRT",
    "r": "0.3333333333",
    "g": "1",
    "b": "0.6666666667",
    "temp-avg-x": "",
    "em-avg-y": "-12,48496283",
    "temp-high-x": "",
    "em-high-y": "-71,72017286",
    "temp-low-x": "",
    "em-low-y": "46,75024719",
    "em-high-y-min": "-71,72017286",
    "em-high-y-max": "-71,72017286",
    "em-low-y-min": "46,75024719",
    "em-low-y-max": "46,75024719"
  },
  {
    "iso-a3": "MUS",
    "r": "0.3333333333",
    "g": "1",
    "b": "0.6666666667",
    "temp-avg-x": "",
    "em-avg-y": "19,79148233",
    "temp-high-x": "",
    "em-high-y": "-9,190869379",
    "temp-low-x": "",
    "em-low-y": "48,77383405",
    "em-high-y-min": "-9,190869379",
    "em-high-y-max": "-9,190869379",
    "em-low-y-min": "48,77383405",
    "em-low-y-max": "48,77383405"
  },
  {
    "iso-a3": "MWI",
    "r": "0.3333333333",
    "g": "1",
    "b": "0.6666666667",
    "temp-avg-x": "",
    "em-avg-y": "138,8922933",
    "temp-high-x": "",
    "em-high-y": "110,8112151",
    "temp-low-x": "",
    "em-low-y": "166,9733715",
    "em-high-y-min": "110,8112151",
    "em-high-y-max": "110,8112151",
    "em-low-y-min": "166,9733715",
    "em-low-y-max": "166,9733715"
  },
  {
    "iso-a3": "MYS",
    "r": "1",
    "g": "0.6666666667",
    "b": "0",
    "temp-avg-x": "",
    "em-avg-y": "20,1605425",
    "temp-high-x": "",
    "em-high-y": "20,1605425",
    "temp-low-x": "",
    "em-low-y": "20,1605425",
    "em-high-y-min": "20,1605425",
    "em-high-y-max": "20,1605425",
    "em-low-y-min": "20,1605425",
    "em-low-y-max": "20,1605425"
  },
  {
    "iso-a3": "NAM",
    "r": "0.3333333333",
    "g": "1",
    "b": "0.6666666667",
    "temp-avg-x": "",
    "em-avg-y": "-35,68019939",
    "temp-high-x": "",
    "em-high-y": "-41,37201498",
    "temp-low-x": "",
    "em-low-y": "-29,9883838",
    "em-high-y-min": "-41,37201498",
    "em-high-y-max": "-41,37201498",
    "em-low-y-min": "-29,9883838",
    "em-low-y-max": "-29,9883838"
  },
  {
    "iso-a3": "NER",
    "r": "0.3333333333",
    "g": "1",
    "b": "0.6666666667",
    "temp-avg-x": "",
    "em-avg-y": "177,3766081",
    "temp-high-x": "",
    "em-high-y": "169,6051442",
    "temp-low-x": "",
    "em-low-y": "185,148072",
    "em-high-y-min": "169,6051442",
    "em-high-y-max": "169,6051442",
    "em-low-y-min": "185,148072",
    "em-low-y-max": "185,148072"
  },
  {
    "iso-a3": "NGA",
    "r": "0.3333333333",
    "g": "1",
    "b": "0.6666666667",
    "temp-avg-x": "",
    "em-avg-y": "6,839062763",
    "temp-high-x": "",
    "em-high-y": "-14,40401931",
    "temp-low-x": "",
    "em-low-y": "28,08214483",
    "em-high-y-min": "-14,40401931",
    "em-high-y-max": "-14,40401931",
    "em-low-y-min": "28,08214483",
    "em-low-y-max": "28,08214483"
  },
  {
    "iso-a3": "NIC",
    "r": "0",
    "g": "1",
    "b": "1",
    "temp-avg-x": "",
    "em-avg-y": "374,0011853",
    "temp-high-x": "",
    "em-high-y": "349,1658182",
    "temp-low-x": "",
    "em-low-y": "398,8365524",
    "em-high-y-min": "349,1658182",
    "em-high-y-max": "349,1658182",
    "em-low-y-min": "398,8365524",
    "em-low-y-max": "398,8365524"
  },
  {
    "iso-a3": "NIU",
    "r": "",
    "g": "",
    "b": "",
    "temp-avg-x": "",
    "em-avg-y": "26,82903163",
    "temp-high-x": "",
    "em-high-y": "-4,754511935",
    "temp-low-x": "",
    "em-low-y": "58,4125752",
    "em-high-y-min": "-4,754511935",
    "em-high-y-max": "-4,754511935",
    "em-low-y-min": "58,4125752",
    "em-low-y-max": "58,4125752"
  },
  {
    "iso-a3": "NLD",
    "r": "0",
    "g": "0.3333333333",
    "b": "1",
    "temp-avg-x": "",
    "em-avg-y": "-49,43308634",
    "temp-high-x": "",
    "em-high-y": "-49,43308634",
    "temp-low-x": "",
    "em-low-y": "-49,43308634",
    "em-high-y-min": "-49,43308634",
    "em-high-y-max": "-49,43308634",
    "em-low-y-min": "-49,43308634",
    "em-low-y-max": "-49,43308634"
  },
  {
    "iso-a3": "NOR",
    "r": "0",
    "g": "0.3333333333",
    "b": "1",
    "temp-avg-x": "",
    "em-avg-y": "-62,49622568",
    "temp-high-x": "",
    "em-high-y": "-64,47010836",
    "temp-low-x": "",
    "em-low-y": "-60,522343",
    "em-high-y-min": "-64,47010836",
    "em-high-y-max": "-64,47010836",
    "em-low-y-min": "-60,522343",
    "em-low-y-max": "-60,522343"
  },
  {
    "iso-a3": "NPL",
    "r": "1",
    "g": "1",
    "b": "0",
    "temp-avg-x": "",
    "em-avg-y": "71,74259578",
    "temp-high-x": "",
    "em-high-y": "71,74259578",
    "temp-low-x": "",
    "em-low-y": "71,74259578",
    "em-high-y-min": "71,74259578",
    "em-high-y-max": "71,74259578",
    "em-low-y-min": "71,74259578",
    "em-low-y-max": "71,74259578"
  },
  {
    "iso-a3": "NRU",
    "r": "",
    "g": "",
    "b": "",
    "temp-avg-x": "",
    "em-avg-y": "47,66911081",
    "temp-high-x": "",
    "em-high-y": "47,66911081",
    "temp-low-x": "",
    "em-low-y": "47,66911081",
    "em-high-y-min": "47,66911081",
    "em-high-y-max": "47,66911081",
    "em-low-y-min": "47,66911081",
    "em-low-y-max": "47,66911081"
  },
  {
    "iso-a3": "NZL",
    "r": "0",
    "g": "0",
    "b": "0.6666666667",
    "temp-avg-x": "",
    "em-avg-y": "-33,83763234",
    "temp-high-x": "",
    "em-high-y": "-33,83763234",
    "temp-low-x": "",
    "em-low-y": "-33,83763234",
    "em-high-y-min": "-33,83763234",
    "em-high-y-max": "-33,83763234",
    "em-low-y-min": "-33,83763234",
    "em-low-y-max": "-33,83763234"
  },
  {
    "iso-a3": "OMN",
    "r": "0.6666666667",
    "g": "1",
    "b": "0.3333333333",
    "temp-avg-x": "",
    "em-avg-y": "74,55150817",
    "temp-high-x": "",
    "em-high-y": "74,55150817",
    "temp-low-x": "",
    "em-low-y": "74,55150817",
    "em-high-y-min": "74,55150817",
    "em-high-y-max": "74,55150817",
    "em-low-y-min": "74,55150817",
    "em-low-y-max": "74,55150817"
  },
  {
    "iso-a3": "PAK",
    "r": "1",
    "g": "1",
    "b": "0",
    "temp-avg-x": "",
    "em-avg-y": "181,0179733",
    "temp-high-x": "",
    "em-high-y": "107,7193021",
    "temp-low-x": "",
    "em-low-y": "254,3166445",
    "em-high-y-min": "107,7193021",
    "em-high-y-max": "107,7193021",
    "em-low-y-min": "254,3166445",
    "em-low-y-max": "254,3166445"
  },
  {
    "iso-a3": "PAN",
    "r": "0",
    "g": "1",
    "b": "1",
    "temp-avg-x": "",
    "em-avg-y": "107,02327",
    "temp-high-x": "",
    "em-high-y": "98,48301469",
    "temp-low-x": "",
    "em-low-y": "115,5635252",
    "em-high-y-min": "98,48301469",
    "em-high-y-max": "98,48301469",
    "em-low-y-min": "115,5635252",
    "em-low-y-max": "115,5635252"
  },
  {
    "iso-a3": "PER",
    "r": "0",
    "g": "1",
    "b": "1",
    "temp-avg-x": "",
    "em-avg-y": "17,55037686",
    "temp-high-x": "",
    "em-high-y": "0,260143742",
    "temp-low-x": "",
    "em-low-y": "34,84060999",
    "em-high-y-min": "0,260143742",
    "em-high-y-max": "0,260143742",
    "em-low-y-min": "34,84060999",
    "em-low-y-max": "34,84060999"
  },
  {
    "iso-a3": "PHL",
    "r": "1",
    "g": "0.6666666667",
    "b": "0",
    "temp-avg-x": "",
    "em-avg-y": "-11,1800867",
    "temp-high-x": "",
    "em-high-y": "-132,1678263",
    "temp-low-x": "",
    "em-low-y": "109,8076529",
    "em-high-y-min": "-132,1678263",
    "em-high-y-max": "-132,1678263",
    "em-low-y-min": "109,8076529",
    "em-low-y-max": "109,8076529"
  },
  {
    "iso-a3": "PLW",
    "r": "",
    "g": "",
    "b": "",
    "temp-avg-x": "",
    "em-avg-y": "-28,92182421",
    "temp-high-x": "",
    "em-high-y": "-28,92182421",
    "temp-low-x": "",
    "em-low-y": "-28,92182421",
    "em-high-y-min": "-28,92182421",
    "em-high-y-max": "-28,92182421",
    "em-low-y-min": "-28,92182421",
    "em-low-y-max": "-28,92182421"
  },
  {
    "iso-a3": "PNG",
    "r": "1",
    "g": "0.6666666667",
    "b": "0",
    "temp-avg-x": "",
    "em-avg-y": "70,02875364",
    "temp-high-x": "",
    "em-high-y": "10,71650849",
    "temp-low-x": "",
    "em-low-y": "129,3409988",
    "em-high-y-min": "10,71650849",
    "em-high-y-max": "10,71650849",
    "em-low-y-min": "129,3409988",
    "em-low-y-max": "129,3409988"
  },
  {
    "iso-a3": "POL",
    "r": "0",
    "g": "0",
    "b": "1",
    "temp-avg-x": "",
    "em-avg-y": "-37,47491749",
    "temp-high-x": "",
    "em-high-y": "-37,47491749",
    "temp-low-x": "",
    "em-low-y": "-37,47491749",
    "em-high-y-min": "-37,47491749",
    "em-high-y-max": "-37,47491749",
    "em-low-y-min": "-37,47491749",
    "em-low-y-max": "-37,47491749"
  },
  {
    "iso-a3": "PRK",
    "r": "",
    "g": "",
    "b": "",
    "temp-avg-x": "",
    "em-avg-y": "99,22827771",
    "temp-high-x": "",
    "em-high-y": "44,22204324",
    "temp-low-x": "",
    "em-low-y": "154,2345122",
    "em-high-y-min": "44,22204324",
    "em-high-y-max": "44,22204324",
    "em-low-y-min": "154,2345122",
    "em-low-y-max": "154,2345122"
  },
  {
    "iso-a3": "PRT",
    "r": "0",
    "g": "0.3333333333",
    "b": "1",
    "temp-avg-x": "",
    "em-avg-y": "-28,18447242",
    "temp-high-x": "",
    "em-high-y": "-28,18447242",
    "temp-low-x": "",
    "em-low-y": "-28,18447242",
    "em-high-y-min": "-28,18447242",
    "em-high-y-max": "-28,18447242",
    "em-low-y-min": "-28,18447242",
    "em-low-y-max": "-28,18447242"
  },
  {
    "iso-a3": "PRY",
    "r": "0",
    "g": "1",
    "b": "1",
    "temp-avg-x": "",
    "em-avg-y": "12,73042369",
    "temp-high-x": "",
    "em-high-y": "-1,407674137",
    "temp-low-x": "",
    "em-low-y": "26,86852152",
    "em-high-y-min": "-1,407674137",
    "em-high-y-max": "-1,407674137",
    "em-low-y-min": "26,86852152",
    "em-low-y-max": "26,86852152"
  },
  {
    "iso-a3": "PSE",
    "r": "",
    "g": "",
    "b": "",
    "temp-avg-x": "",
    "em-avg-y": "278,9289024",
    "temp-high-x": "",
    "em-high-y": "245,0347594",
    "temp-low-x": "",
    "em-low-y": "312,8230455",
    "em-high-y-min": "277,7864032",
    "em-high-y-max": "212,2831156",
    "em-low-y-min": "363,0930104",
    "em-low-y-max": "262,5530805"
  },
  {
    "iso-a3": "QAT",
    "r": "",
    "g": "",
    "b": "",
    "temp-avg-x": "",
    "em-avg-y": "51,7121649",
    "temp-high-x": "",
    "em-high-y": "51,7121649",
    "temp-low-x": "",
    "em-low-y": "51,7121649",
    "em-high-y-min": "51,7121649",
    "em-high-y-max": "51,7121649",
    "em-low-y-min": "51,7121649",
    "em-low-y-max": "51,7121649"
  },
  {
    "iso-a3": "ROU",
    "r": "0",
    "g": "0",
    "b": "1",
    "temp-avg-x": "",
    "em-avg-y": "-14,33098879",
    "temp-high-x": "",
    "em-high-y": "-14,33098879",
    "temp-low-x": "",
    "em-low-y": "-14,33098879",
    "em-high-y-min": "-14,33098879",
    "em-high-y-max": "-14,33098879",
    "em-low-y-min": "-14,33098879",
    "em-low-y-max": "-14,33098879"
  },
  {
    "iso-a3": "RUS",
    "r": "0",
    "g": "0",
    "b": "1",
    "temp-avg-x": "",
    "em-avg-y": "16,00263304",
    "temp-high-x": "",
    "em-high-y": "16,00263304",
    "temp-low-x": "",
    "em-low-y": "16,00263304",
    "em-high-y-min": "16,00263304",
    "em-high-y-max": "16,00263304",
    "em-low-y-min": "16,00263304",
    "em-low-y-max": "16,00263304"
  },
  {
    "iso-a3": "RWA",
    "r": "0.3333333333",
    "g": "1",
    "b": "0.6666666667",
    "temp-avg-x": "",
    "em-avg-y": "52,63752731",
    "temp-high-x": "",
    "em-high-y": "31,39661773",
    "temp-low-x": "",
    "em-low-y": "73,87843689",
    "em-high-y-min": "31,39661773",
    "em-high-y-max": "31,39661773",
    "em-low-y-min": "73,87843689",
    "em-low-y-max": "73,87843689"
  },
  {
    "iso-a3": "SAU",
    "r": "0.6666666667",
    "g": "1",
    "b": "0.3333333333",
    "temp-avg-x": "",
    "em-avg-y": "3,383126872",
    "temp-high-x": "",
    "em-high-y": "3,383126872",
    "temp-low-x": "",
    "em-low-y": "3,383126872",
    "em-high-y-min": "46,90184946",
    "em-high-y-max": "-40,13559572",
    "em-low-y-min": "46,90184946",
    "em-low-y-max": "-40,13559572"
  },
  {
    "iso-a3": "SDN",
    "r": "0.6666666667",
    "g": "1",
    "b": "0.3333333333",
    "temp-avg-x": "",
    "em-avg-y": "53,10653543",
    "temp-high-x": "",
    "em-high-y": "45,92512375",
    "temp-low-x": "",
    "em-low-y": "60,2879471",
    "em-high-y-min": "45,92512375",
    "em-high-y-max": "45,92512375",
    "em-low-y-min": "60,2879471",
    "em-low-y-max": "60,2879471"
  },
  {
    "iso-a3": "SEN",
    "r": "0.3333333333",
    "g": "1",
    "b": "0.6666666667",
    "temp-avg-x": "",
    "em-avg-y": "63,00185765",
    "temp-high-x": "",
    "em-high-y": "40,57040922",
    "temp-low-x": "",
    "em-low-y": "85,43330607",
    "em-high-y-min": "40,57040922",
    "em-high-y-max": "40,57040922",
    "em-low-y-min": "85,43330607",
    "em-low-y-max": "85,43330607"
  },
  {
    "iso-a3": "SGP",
    "r": "1",
    "g": "0.6666666667",
    "b": "0",
    "temp-avg-x": "",
    "em-avg-y": "21,21754181",
    "temp-high-x": "",
    "em-high-y": "21,21754181",
    "temp-low-x": "",
    "em-low-y": "21,21754181",
    "em-high-y-min": "21,21754181",
    "em-high-y-max": "21,21754181",
    "em-low-y-min": "21,21754181",
    "em-low-y-max": "21,21754181"
  },
  {
    "iso-a3": "SLB",
    "r": "1",
    "g": "0.6666666667",
    "b": "0",
    "temp-avg-x": "",
    "em-avg-y": "-15,74689055",
    "temp-high-x": "",
    "em-high-y": "-58,34680069",
    "temp-low-x": "",
    "em-low-y": "26,85301958",
    "em-high-y-min": "-58,34680069",
    "em-high-y-max": "-58,34680069",
    "em-low-y-min": "26,85301958",
    "em-low-y-max": "26,85301958"
  },
  {
    "iso-a3": "SLE",
    "r": "0.3333333333",
    "g": "1",
    "b": "0.6666666667",
    "temp-avg-x": "",
    "em-avg-y": "137,6633101",
    "temp-high-x": "",
    "em-high-y": "137,6633101",
    "temp-low-x": "",
    "em-low-y": "137,6633101",
    "em-high-y-min": "137,6633101",
    "em-high-y-max": "137,6633101",
    "em-low-y-min": "137,6633101",
    "em-low-y-max": "137,6633101"
  },
  {
    "iso-a3": "SLV",
    "r": "0",
    "g": "1",
    "b": "1",
    "temp-avg-x": "",
    "em-avg-y": "34,38415349",
    "temp-high-x": "",
    "em-high-y": "33,66034603",
    "temp-low-x": "",
    "em-low-y": "35,10796094",
    "em-high-y-min": "33,66034603",
    "em-high-y-max": "33,66034603",
    "em-low-y-min": "35,10796094",
    "em-low-y-max": "35,10796094"
  },
  {
    "iso-a3": "SMR",
    "r": "",
    "g": "",
    "b": "",
    "temp-avg-x": "",
    "em-avg-y": "-11,58246835",
    "temp-high-x": "",
    "em-high-y": "-11,58246835",
    "temp-low-x": "",
    "em-low-y": "-11,58246835",
    "em-high-y-min": "-11,58246835",
    "em-high-y-max": "-11,58246835",
    "em-low-y-min": "-11,58246835",
    "em-low-y-max": "-11,58246835"
  },
  {
    "iso-a3": "SOM",
    "r": "0.3333333333",
    "g": "1",
    "b": "0.6666666667",
    "temp-avg-x": "",
    "em-avg-y": "212,8753104",
    "temp-high-x": "",
    "em-high-y": "157,6756138",
    "temp-low-x": "",
    "em-low-y": "268,075007",
    "em-high-y-min": "157,6756138",
    "em-high-y-max": "157,6756138",
    "em-low-y-min": "268,075007",
    "em-low-y-max": "268,075007"
  },
  {
    "iso-a3": "SRB",
    "r": "0",
    "g": "0",
    "b": "1",
    "temp-avg-x": "",
    "em-avg-y": "-13,20000059",
    "temp-high-x": "",
    "em-high-y": "-13,20000059",
    "temp-low-x": "",
    "em-low-y": "-13,20000059",
    "em-high-y-min": "-13,20000059",
    "em-high-y-max": "-13,20000059",
    "em-low-y-min": "-13,20000059",
    "em-low-y-max": "-13,20000059"
  },
  {
    "iso-a3": "SSD",
    "r": "",
    "g": "",
    "b": "",
    "temp-avg-x": "",
    "em-avg-y": "66,42093258",
    "temp-high-x": "",
    "em-high-y": "66,42093258",
    "temp-low-x": "",
    "em-low-y": "66,42093258",
    "em-high-y-min": "66,42093258",
    "em-high-y-max": "66,42093258",
    "em-low-y-min": "66,42093258",
    "em-low-y-max": "66,42093258"
  },
  {
    "iso-a3": "STP",
    "r": "0.3333333333",
    "g": "1",
    "b": "0.6666666667",
    "temp-avg-x": "",
    "em-avg-y": "115,6201651",
    "temp-high-x": "",
    "em-high-y": "81,96841953",
    "temp-low-x": "",
    "em-low-y": "149,2719108",
    "em-high-y-min": "81,96841953",
    "em-high-y-max": "81,96841953",
    "em-low-y-min": "149,2719108",
    "em-low-y-max": "149,2719108"
  },
  {
    "iso-a3": "SUR",
    "r": "0",
    "g": "1",
    "b": "1",
    "temp-avg-x": "",
    "em-avg-y": "90,31023517",
    "temp-high-x": "",
    "em-high-y": "90,31023517",
    "temp-low-x": "",
    "em-low-y": "90,31023517",
    "em-high-y-min": "90,31023517",
    "em-high-y-max": "90,31023517",
    "em-low-y-min": "90,31023517",
    "em-low-y-max": "90,31023517"
  },
  {
    "iso-a3": "SVK",
    "r": "0",
    "g": "0",
    "b": "1",
    "temp-avg-x": "",
    "em-avg-y": "-39,52827094",
    "temp-high-x": "",
    "em-high-y": "-39,52827094",
    "temp-low-x": "",
    "em-low-y": "-39,52827094",
    "em-high-y-min": "-39,52827094",
    "em-high-y-max": "-39,52827094",
    "em-low-y-min": "-39,52827094",
    "em-low-y-max": "-39,52827094"
  },
  {
    "iso-a3": "SVN",
    "r": "0",
    "g": "0",
    "b": "1",
    "temp-avg-x": "",
    "em-avg-y": "-29,77803241",
    "temp-high-x": "",
    "em-high-y": "-29,77803241",
    "temp-low-x": "",
    "em-low-y": "-29,77803241",
    "em-high-y-min": "-29,77803241",
    "em-high-y-max": "-29,77803241",
    "em-low-y-min": "-29,77803241",
    "em-low-y-max": "-29,77803241"
  },
  {
    "iso-a3": "SWE",
    "r": "0",
    "g": "0.3333333333",
    "b": "1",
    "temp-avg-x": "",
    "em-avg-y": "-34,31909608",
    "temp-high-x": "",
    "em-high-y": "-34,31909608",
    "temp-low-x": "",
    "em-low-y": "-34,31909608",
    "em-high-y-min": "-34,31909608",
    "em-high-y-max": "-34,31909608",
    "em-low-y-min": "-34,31909608",
    "em-low-y-max": "-34,31909608"
  },
  {
    "iso-a3": "SWZ",
    "r": "0.3333333333",
    "g": "1",
    "b": "0.6666666667",
    "temp-avg-x": "",
    "em-avg-y": "66,81604297",
    "temp-high-x": "",
    "em-high-y": "58,52132619",
    "temp-low-x": "",
    "em-low-y": "75,11075975",
    "em-high-y-min": "58,52132619",
    "em-high-y-max": "58,52132619",
    "em-low-y-min": "75,11075975",
    "em-low-y-max": "75,11075975"
  },
  {
    "iso-a3": "SYC",
    "r": "",
    "g": "",
    "b": "",
    "temp-avg-x": "",
    "em-avg-y": "89,56776345",
    "temp-high-x": "",
    "em-high-y": "61,63816868",
    "temp-low-x": "",
    "em-low-y": "117,4973582",
    "em-high-y-min": "61,63816868",
    "em-high-y-max": "61,63816868",
    "em-low-y-min": "117,4973582",
    "em-low-y-max": "117,4973582"
  },
  {
    "iso-a3": "SYR",
    "r": "0.6666666667",
    "g": "1",
    "b": "0.3333333333",
    "temp-avg-x": "",
    "em-avg-y": "-3,070465692",
    "temp-high-x": "",
    "em-high-y": "-3,070465692",
    "temp-low-x": "",
    "em-low-y": "-3,070465692",
    "em-high-y-min": "-3,070465692",
    "em-high-y-max": "-3,070465692",
    "em-low-y-min": "-3,070465692",
    "em-low-y-max": "-3,070465692"
  },
  {
    "iso-a3": "TCD",
    "r": "0.3333333333",
    "g": "1",
    "b": "0.6666666667",
    "temp-avg-x": "",
    "em-avg-y": "165,2624693",
    "temp-high-x": "",
    "em-high-y": "137,5880279",
    "temp-low-x": "",
    "em-low-y": "192,9369106",
    "em-high-y-min": "137,5880279",
    "em-high-y-max": "137,5880279",
    "em-low-y-min": "192,9369106",
    "em-low-y-max": "192,9369106"
  },
  {
    "iso-a3": "TGO",
    "r": "0.3333333333",
    "g": "1",
    "b": "0.6666666667",
    "temp-avg-x": "",
    "em-avg-y": "25,84836902",
    "temp-high-x": "",
    "em-high-y": "-26,93875857",
    "temp-low-x": "",
    "em-low-y": "78,63549661",
    "em-high-y-min": "-26,93875857",
    "em-high-y-max": "-26,93875857",
    "em-low-y-min": "78,63549661",
    "em-low-y-max": "78,63549661"
  },
  {
    "iso-a3": "THA",
    "r": "1",
    "g": "0.6666666667",
    "b": "0",
    "temp-avg-x": "",
    "em-avg-y": "12,10540785",
    "temp-high-x": "",
    "em-high-y": "8,489104308",
    "temp-low-x": "",
    "em-low-y": "15,7217114",
    "em-high-y-min": "8,489104308",
    "em-high-y-max": "8,489104308",
    "em-low-y-min": "15,7217114",
    "em-low-y-max": "15,7217114"
  },
  {
    "iso-a3": "TJK",
    "r": "0",
    "g": "0",
    "b": "1",
    "temp-avg-x": "",
    "em-avg-y": "126,557261",
    "temp-high-x": "",
    "em-high-y": "109,5426255",
    "temp-low-x": "",
    "em-low-y": "143,5718965",
    "em-high-y-min": "126,557261",
    "em-high-y-max": "92,52799003",
    "em-low-y-min": "160,5865319",
    "em-low-y-max": "126,557261"
  },
  {
    "iso-a3": "TKM",
    "r": "0",
    "g": "0",
    "b": "1",
    "temp-avg-x": "",
    "em-avg-y": "36,34632303",
    "temp-high-x": "",
    "em-high-y": "27,9839386",
    "temp-low-x": "",
    "em-low-y": "44,70870746",
    "em-high-y-min": "27,9839386",
    "em-high-y-max": "27,9839386",
    "em-low-y-min": "44,70870746",
    "em-low-y-max": "44,70870746"
  },
  {
    "iso-a3": "TLS",
    "r": "1",
    "g": "0.6666666667",
    "b": "0",
    "temp-avg-x": "",
    "em-avg-y": "-158,2673812",
    "temp-high-x": "",
    "em-high-y": "-158,2673812",
    "temp-low-x": "",
    "em-low-y": "-158,2673812",
    "em-high-y-min": "-158,2673812",
    "em-high-y-max": "-158,2673812",
    "em-low-y-min": "-158,2673812",
    "em-low-y-max": "-158,2673812"
  },
  {
    "iso-a3": "TON",
    "r": "1",
    "g": "0.6666666667",
    "b": "0",
    "temp-avg-x": "",
    "em-avg-y": "15,81572934",
    "temp-high-x": "",
    "em-high-y": "15,81572934",
    "temp-low-x": "",
    "em-low-y": "15,81572934",
    "em-high-y-min": "15,81572934",
    "em-high-y-max": "15,81572934",
    "em-low-y-min": "15,81572934",
    "em-low-y-max": "15,81572934"
  },
  {
    "iso-a3": "TTO",
    "r": "0",
    "g": "1",
    "b": "1",
    "temp-avg-x": "",
    "em-avg-y": "19,08840686",
    "temp-high-x": "",
    "em-high-y": "10,44952299",
    "temp-low-x": "",
    "em-low-y": "27,72729074",
    "em-high-y-min": "10,44952299",
    "em-high-y-max": "10,44952299",
    "em-low-y-min": "27,72729074",
    "em-low-y-max": "27,72729074"
  },
  {
    "iso-a3": "TUN",
    "r": "0.6666666667",
    "g": "1",
    "b": "0.3333333333",
    "temp-avg-x": "",
    "em-avg-y": "26,52057449",
    "temp-high-x": "",
    "em-high-y": "10,01604176",
    "temp-low-x": "",
    "em-low-y": "43,02510722",
    "em-high-y-min": "37,41673278",
    "em-high-y-max": "-17,38464926",
    "em-low-y-min": "79,44727416",
    "em-low-y-max": "6,60294027"
  },
  {
    "iso-a3": "TUR",
    "r": "0",
    "g": "0.3333333333",
    "b": "1",
    "temp-avg-x": "",
    "em-avg-y": "142,9613844",
    "temp-high-x": "",
    "em-high-y": "142,9613844",
    "temp-low-x": "",
    "em-low-y": "142,9613844",
    "em-high-y-min": "142,9613844",
    "em-high-y-max": "142,9613844",
    "em-low-y-min": "142,9613844",
    "em-low-y-max": "142,9613844"
  },
  {
    "iso-a3": "TUV",
    "r": "",
    "g": "",
    "b": "",
    "temp-avg-x": "",
    "em-avg-y": "-2,05693456",
    "temp-high-x": "",
    "em-high-y": "-2,05693456",
    "temp-low-x": "",
    "em-low-y": "-2,05693456",
    "em-high-y-min": "-0,364520049",
    "em-high-y-max": "-3,749349071",
    "em-low-y-min": "-0,364520049",
    "em-low-y-max": "-3,749349071"
  },
  {
    "iso-a3": "TZA",
    "r": "0.3333333333",
    "g": "1",
    "b": "0.6666666667",
    "temp-avg-x": "",
    "em-avg-y": "86,78974196",
    "temp-high-x": "",
    "em-high-y": "74,5479387",
    "temp-low-x": "",
    "em-low-y": "99,03154522",
    "em-high-y-min": "80,49843661",
    "em-high-y-max": "68,59744079",
    "em-low-y-min": "99,03154522",
    "em-low-y-max": "99,03154522"
  },
  {
    "iso-a3": "UGA",
    "r": "0.3333333333",
    "g": "1",
    "b": "0.6666666667",
    "temp-avg-x": "",
    "em-avg-y": "105,1487566",
    "temp-high-x": "",
    "em-high-y": "95,94905917",
    "temp-low-x": "",
    "em-low-y": "114,3484541",
    "em-high-y-min": "95,94905917",
    "em-high-y-max": "95,94905917",
    "em-low-y-min": "114,3484541",
    "em-low-y-max": "114,3484541"
  },
  {
    "iso-a3": "UKR",
    "r": "0",
    "g": "0",
    "b": "1",
    "temp-avg-x": "",
    "em-avg-y": "-30,22889822",
    "temp-high-x": "",
    "em-high-y": "-30,22889822",
    "temp-low-x": "",
    "em-low-y": "-30,22889822",
    "em-high-y-min": "-30,22889822",
    "em-high-y-max": "-30,22889822",
    "em-low-y-min": "-30,22889822",
    "em-low-y-max": "-30,22889822"
  },
  {
    "iso-a3": "URY",
    "r": "0",
    "g": "1",
    "b": "1",
    "temp-avg-x": "",
    "em-avg-y": "2,915627534",
    "temp-high-x": "",
    "em-high-y": "-5,396995712",
    "temp-low-x": "",
    "em-low-y": "11,22825078",
    "em-high-y-min": "-5,396995712",
    "em-high-y-max": "-5,396995712",
    "em-low-y-min": "11,22825078",
    "em-low-y-max": "11,22825078"
  },
  {
    "iso-a3": "USA",
    "r": "0",
    "g": "0.6666666667",
    "b": "1",
    "temp-avg-x": "",
    "em-avg-y": "-38,77250214",
    "temp-high-x": "",
    "em-high-y": "-38,77250214",
    "temp-low-x": "",
    "em-low-y": "-38,77250214",
    "em-high-y-min": "-37,77413793",
    "em-high-y-max": "-39,77086635",
    "em-low-y-min": "-37,77413793",
    "em-low-y-max": "-39,77086635"
  },
  {
    "iso-a3": "UZB",
    "r": "0",
    "g": "0",
    "b": "1",
    "temp-avg-x": "",
    "em-avg-y": "94,9790377",
    "temp-high-x": "",
    "em-high-y": "94,9790377",
    "temp-low-x": "",
    "em-low-y": "94,9790377",
    "em-high-y-min": "94,9790377",
    "em-high-y-max": "94,9790377",
    "em-low-y-min": "94,9790377",
    "em-low-y-max": "94,9790377"
  },
  {
    "iso-a3": "VCT",
    "r": "0",
    "g": "1",
    "b": "1",
    "temp-avg-x": "",
    "em-avg-y": "54,74319044",
    "temp-high-x": "",
    "em-high-y": "54,74319044",
    "temp-low-x": "",
    "em-low-y": "54,74319044",
    "em-high-y-min": "54,74319044",
    "em-high-y-max": "54,74319044",
    "em-low-y-min": "54,74319044",
    "em-low-y-max": "54,74319044"
  },
  {
    "iso-a3": "VEN",
    "r": "0",
    "g": "1",
    "b": "1",
    "temp-avg-x": "",
    "em-avg-y": "47,81430376",
    "temp-high-x": "",
    "em-high-y": "35,54318131",
    "temp-low-x": "",
    "em-low-y": "60,08542621",
    "em-high-y-min": "35,54318131",
    "em-high-y-max": "35,54318131",
    "em-low-y-min": "60,08542621",
    "em-low-y-max": "60,08542621"
  },
  {
    "iso-a3": "VNM",
    "r": "1",
    "g": "0.6666666667",
    "b": "0",
    "temp-avg-x": "",
    "em-avg-y": "175,1453757",
    "temp-high-x": "",
    "em-high-y": "143,6876339",
    "temp-low-x": "",
    "em-low-y": "206,6031175",
    "em-high-y-min": "143,6876339",
    "em-high-y-max": "143,6876339",
    "em-low-y-min": "206,6031175",
    "em-low-y-max": "206,6031175"
  },
  {
    "iso-a3": "VUT",
    "r": "1",
    "g": "0.6666666667",
    "b": "0",
    "temp-avg-x": "",
    "em-avg-y": "-23,00811097",
    "temp-high-x": "",
    "em-high-y": "-33,22748913",
    "temp-low-x": "",
    "em-low-y": "-12,78873281",
    "em-high-y-min": "-33,22748913",
    "em-high-y-max": "-33,22748913",
    "em-low-y-min": "-12,78873281",
    "em-low-y-max": "-12,78873281"
  },
  {
    "iso-a3": "WSM",
    "r": "1",
    "g": "0.6666666667",
    "b": "0",
    "temp-avg-x": "",
    "em-avg-y": "26,62935116",
    "temp-high-x": "",
    "em-high-y": "-31,92443494",
    "temp-low-x": "",
    "em-low-y": "85,18313727",
    "em-high-y-min": "-31,92443494",
    "em-high-y-max": "-31,92443494",
    "em-low-y-min": "85,18313727",
    "em-low-y-max": "85,18313727"
  },
  {
    "iso-a3": "YEM",
    "r": "0.6666666667",
    "g": "1",
    "b": "0.3333333333",
    "temp-avg-x": "",
    "em-avg-y": "-14,53596344",
    "temp-high-x": "",
    "em-high-y": "-20,54154464",
    "temp-low-x": "",
    "em-low-y": "-8,530382238",
    "em-high-y-min": "-20,54154464",
    "em-high-y-max": "-20,54154464",
    "em-low-y-min": "-8,530382238",
    "em-low-y-max": "-8,530382238"
  },
  {
    "iso-a3": "ZAF",
    "r": "0.3333333333",
    "g": "1",
    "b": "0.6666666667",
    "temp-avg-x": "",
    "em-avg-y": "5,65247169",
    "temp-high-x": "",
    "em-high-y": "-24,38191065",
    "temp-low-x": "",
    "em-low-y": "35,68685403",
    "em-high-y-min": "-17,86228884",
    "em-high-y-max": "-30,90153247",
    "em-low-y-min": "35,68685403",
    "em-low-y-max": "35,68685403"
  },
  {
    "iso-a3": "ZMB",
    "r": "0.3333333333",
    "g": "1",
    "b": "0.6666666667",
    "temp-avg-x": "",
    "em-avg-y": "70,53536207",
    "temp-high-x": "",
    "em-high-y": "41,93787713",
    "temp-low-x": "",
    "em-low-y": "99,13284702",
    "em-high-y-min": "41,93787713",
    "em-high-y-max": "41,93787713",
    "em-low-y-min": "99,13284702",
    "em-low-y-max": "99,13284702"
  },
  {
    "iso-a3": "ZWE",
    "r": "",
    "g": "",
    "b": "",
    "temp-avg-x": "",
    "em-avg-y": "51,28399026",
    "temp-high-x": "",
    "em-high-y": "41,54625467",
    "temp-low-x": "",
    "em-low-y": "61,02172584",
    "em-high-y-min": "41,54625467",
    "em-high-y-max": "41,54625467",
    "em-low-y-min": "61,02172584",
    "em-low-y-max": "61,02172584"
  },
  {
    "iso-a3": "EU27",
    "r": 0,
    "g": 0.3333333333,
    "b": 1,
    "temp-avg-x": 2.179476,
    "em-avg-y": -46.95150729,
    "temp-high-x": null,
    "em-high-y": null,
    "temp-low-x": 2.179476,
    "em-low-y": -46.95150729,
    "em-high-y-min": null,
    "em-high-y-max": null,
    "em-low-y-min": -48.67810729,
    "em-low-y-max": -45.46600862
  },
  {
    "iso-a3": "EU28",
    "r": 0,
    "g": 0.3333333333,
    "b": 1,
    "temp-avg-x": null,
    "em-avg-y": null,
    "temp-high-x": null,
    "em-high-y": null,
    "temp-low-x": null,
    "em-low-y": null
  }
]
